{
    "project_path": "/Users/gssakash/Desktop/test-env/frontend-theming-29-jul/projects/Blockchain_data_analyzer_1722421125",
    "project_name": "Blockchain_data_analyzer_1722421125",
    "project_description": "add an app to analyse new blockchain information",
    "creation_time": "2024-07-31 15:48:45.965143",
    "current_state": "The current state of the application has a navbar and a header",
    "selected_starter_template_id": "stellar",
    "frontend_theme_prompt": "The image uses a vibrant color scheme with various shades of pink and purple, creating a surreal, cosmic landscape featuring planets and jagged mountains. The style is highly detailed and fantastical, with a strong focus on luminous, dream-like elements."
}